[
	{
		"IdCanton": 101,
		"IdProvincia": 1,
		"Descripcion": "San José"
	},
	{
		"IdCanton": 102,
		"IdProvincia": 1,
		"Descripcion": "Escazú"
	},
	{
		"IdCanton": 103,
		"IdProvincia": 1,
		"Descripcion": "Desamparados"
	},
	{
		"IdCanton": 104,
		"IdProvincia": 1,
		"Descripcion": "Puriscal"
	},
	{
		"IdCanton": 105,
		"IdProvincia": 1,
		"Descripcion": "Tarrazú"
	},
	{
		"IdCanton": 106,
		"IdProvincia": 1,
		"Descripcion": "Aserrí"
	},
	{
		"IdCanton": 107,
		"IdProvincia": 1,
		"Descripcion": "Mora"
	},
	{
		"IdCanton": 108,
		"IdProvincia": 1,
		"Descripcion": "Goicoechea"
	},
	{
		"IdCanton": 109,
		"IdProvincia": 1,
		"Descripcion": "Santa Ana"
	},
	{
		"IdCanton": 110,
		"IdProvincia": 1,
		"Descripcion": "Alajuelita"
	},
	{
		"IdCanton": 111,
		"IdProvincia": 1,
		"Descripcion": "Vázquez de Coronado"
	},
	{
		"IdCanton": 112,
		"IdProvincia": 1,
		"Descripcion": "Acosta"
	},
	{
		"IdCanton": 113,
		"IdProvincia": 1,
		"Descripcion": "Tibás"
	},
	{
		"IdCanton": 114,
		"IdProvincia": 1,
		"Descripcion": "Moravia"
	},
	{
		"IdCanton": 115,
		"IdProvincia": 1,
		"Descripcion": "Montes de Oca"
	},
	{
		"IdCanton": 116,
		"IdProvincia": 1,
		"Descripcion": "Turrubares"
	},
	{
		"IdCanton": 117,
		"IdProvincia": 1,
		"Descripcion": "Dota"
	},
	{
		"IdCanton": 118,
		"IdProvincia": 1,
		"Descripcion": "Curridabat"
	},
	{
		"IdCanton": 119,
		"IdProvincia": 1,
		"Descripcion": "Pérez Zeledón"
	},
	{
		"IdCanton": 120,
		"IdProvincia": 1,
		"Descripcion": "León Cortés Castro"
	},
	{
		"IdCanton": 201,
		"IdProvincia": 2,
		"Descripcion": "Alajuela"
	},
	{
		"IdCanton": 202,
		"IdProvincia": 2,
		"Descripcion": "San Ramón"
	},
	{
		"IdCanton": 203,
		"IdProvincia": 2,
		"Descripcion": "Grecia"
	},
	{
		"IdCanton": 204,
		"IdProvincia": 2,
		"Descripcion": "San Mateo"
	},
	{
		"IdCanton": 205,
		"IdProvincia": 2,
		"Descripcion": "Atenas"
	},
	{
		"IdCanton": 206,
		"IdProvincia": 2,
		"Descripcion": "Naranjo"
	},
	{
		"IdCanton": 207,
		"IdProvincia": 2,
		"Descripcion": "Palmares"
	},
	{
		"IdCanton": 208,
		"IdProvincia": 2,
		"Descripcion": "Poás"
	},
	{
		"IdCanton": 209,
		"IdProvincia": 2,
		"Descripcion": "Orotina"
	},
	{
		"IdCanton": 210,
		"IdProvincia": 2,
		"Descripcion": "San Carlos"
	},
	{
		"IdCanton": 211,
		"IdProvincia": 2,
		"Descripcion": "Zarcero"
	},
	{
		"IdCanton": 212,
		"IdProvincia": 2,
		"Descripcion": "Valverde Vega"
	},
	{
		"IdCanton": 213,
		"IdProvincia": 2,
		"Descripcion": "Upala"
	},
	{
		"IdCanton": 214,
		"IdProvincia": 2,
		"Descripcion": "Los Chiles"
	},
	{
		"IdCanton": 215,
		"IdProvincia": 2,
		"Descripcion": "Guatuso"
	},
	{
		"IdCanton": 301,
		"IdProvincia": 3,
		"Descripcion": "Cartago"
	},
	{
		"IdCanton": 302,
		"IdProvincia": 3,
		"Descripcion": "Paraíso"
	},
	{
		"IdCanton": 303,
		"IdProvincia": 3,
		"Descripcion": "La Unión"
	},
	{
		"IdCanton": 304,
		"IdProvincia": 3,
		"Descripcion": "Jiménez"
	},
	{
		"IdCanton": 305,
		"IdProvincia": 3,
		"Descripcion": "Turrialba"
	},
	{
		"IdCanton": 306,
		"IdProvincia": 3,
		"Descripcion": "Alvarado"
	},
	{
		"IdCanton": 307,
		"IdProvincia": 3,
		"Descripcion": "Oreamuno"
	},
	{
		"IdCanton": 308,
		"IdProvincia": 3,
		"Descripcion": "El Guarco"
	},
	{
		"IdCanton": 401,
		"IdProvincia": 4,
		"Descripcion": "Heredia"
	},
	{
		"IdCanton": 402,
		"IdProvincia": 4,
		"Descripcion": "Barva"
	},
	{
		"IdCanton": 403,
		"IdProvincia": 4,
		"Descripcion": "Santo Domingo"
	},
	{
		"IdCanton": 404,
		"IdProvincia": 4,
		"Descripcion": "Santa Bárbara"
	},
	{
		"IdCanton": 405,
		"IdProvincia": 4,
		"Descripcion": "San Rafael"
	},
	{
		"IdCanton": 406,
		"IdProvincia": 4,
		"Descripcion": "San Isidro"
	},
	{
		"IdCanton": 407,
		"IdProvincia": 4,
		"Descripcion": "Belén"
	},
	{
		"IdCanton": 408,
		"IdProvincia": 4,
		"Descripcion": "Flores"
	},
	{
		"IdCanton": 409,
		"IdProvincia": 4,
		"Descripcion": "San Pablo"
	},
	{
		"IdCanton": 410,
		"IdProvincia": 4,
		"Descripcion": "Sarapiquí"
	},
	{
		"IdCanton": 501,
		"IdProvincia": 5,
		"Descripcion": "Liberia"
	},
	{
		"IdCanton": 502,
		"IdProvincia": 5,
		"Descripcion": "Nicoya"
	},
	{
		"IdCanton": 503,
		"IdProvincia": 5,
		"Descripcion": "Santa Cruz"
	},
	{
		"IdCanton": 504,
		"IdProvincia": 5,
		"Descripcion": "Bagaces"
	},
	{
		"IdCanton": 505,
		"IdProvincia": 5,
		"Descripcion": "Carrillo"
	},
	{
		"IdCanton": 506,
		"IdProvincia": 5,
		"Descripcion": "Cañas"
	},
	{
		"IdCanton": 507,
		"IdProvincia": 5,
		"Descripcion": "Abangares"
	},
	{
		"IdCanton": 508,
		"IdProvincia": 5,
		"Descripcion": "Tilarán"
	},
	{
		"IdCanton": 509,
		"IdProvincia": 5,
		"Descripcion": "Nandayure"
	},
	{
		"IdCanton": 510,
		"IdProvincia": 5,
		"Descripcion": "La Cruz"
	},
	{
		"IdCanton": 511,
		"IdProvincia": 5,
		"Descripcion": "Hojancha"
	},
	{
		"IdCanton": 601,
		"IdProvincia": 6,
		"Descripcion": "Puntarenas"
	},
	{
		"IdCanton": 602,
		"IdProvincia": 6,
		"Descripcion": "Esparza"
	},
	{
		"IdCanton": 603,
		"IdProvincia": 6,
		"Descripcion": "Buenos Aires"
	},
	{
		"IdCanton": 604,
		"IdProvincia": 6,
		"Descripcion": "Montes de Oro"
	},
	{
		"IdCanton": 605,
		"IdProvincia": 6,
		"Descripcion": "Osa"
	},
	{
		"IdCanton": 606,
		"IdProvincia": 6,
		"Descripcion": "Quepos"
	},
	{
		"IdCanton": 607,
		"IdProvincia": 6,
		"Descripcion": "Golfito"
	},
	{
		"IdCanton": 608,
		"IdProvincia": 6,
		"Descripcion": "Coto Brus"
	},
	{
		"IdCanton": 609,
		"IdProvincia": 6,
		"Descripcion": "Parrita"
	},
	{
		"IdCanton": 610,
		"IdProvincia": 6,
		"Descripcion": "Corredores"
	},
	{
		"IdCanton": 611,
		"IdProvincia": 6,
		"Descripcion": "Garabito"
	},
	{
		"IdCanton": 701,
		"IdProvincia": 7,
		"Descripcion": "Limón"
	},
	{
		"IdCanton": 702,
		"IdProvincia": 7,
		"Descripcion": "Pococí"
	},
	{
		"IdCanton": 703,
		"IdProvincia": 7,
		"Descripcion": "Siquirres"
	},
	{
		"IdCanton": 704,
		"IdProvincia": 7,
		"Descripcion": "Talamanca"
	},
	{
		"IdCanton": 705,
		"IdProvincia": 7,
		"Descripcion": "Matina"
	},
	{
		"IdCanton": 706,
		"IdProvincia": 7,
		"Descripcion": "Guácimo"
	}
]